aw_api/__init__.py
aw_api/async_client.py
aw_api/client.py
aw_api/dataobjects/__init__.py
aw_api/dataobjects/battalion.py
aw_api/dataobjects/player.py
aw_api/enums.py
aw_api/exceptions.py
aw_api/parser.py
aw_api-2.0.4.dist-info/LICENSE
aw_api-2.0.4.dist-info/METADATA
aw_api-2.0.4.dist-info/WHEEL
aw_api-2.0.4.dist-info/RECORD
